tien/__init__.py
tien/actfunc.py
tien/setup.py
tien-1.0.0.dist-info/METADATA
tien-1.0.0.dist-info/WHEEL
tien-1.0.0.dist-info/top_level.txt
tien-1.0.0.dist-info/RECORD
