Metadata-Version: 2.1
Name: tien
Version: 1.0.0
Summary: simple GANN
Home-page: https://github.com/nakasyou/tien
Author: nakasyou
Author-email: nakasyou1103@gmail.com
License: MIT
Keywords: tien tyen then neural net network learning learn heredity nn ANN GN
Platform: UNKNOWN
Classifier: License :: OSI Approved :: MIT License
Classifier: Programming Language :: Python :: 3.9
Requires-Dist: numpy
